uPyExplorer/About.py
uPyExplorer/Clear.png
uPyExplorer/Copy.png
uPyExplorer/DelFile.png
uPyExplorer/Displ.png
uPyExplorer/Info.py
uPyExplorer/MicroPyTree.py
uPyExplorer/MkDir.png
uPyExplorer/Option.py
uPyExplorer/OptionValues.py
uPyExplorer/Reboot.png
uPyExplorer/Refresh.png
uPyExplorer/ReplCon.py
uPyExplorer/RmDir.png
uPyExplorer/Run.png
uPyExplorer/Screen.py
uPyExplorer/Stop.png
uPyExplorer/Tab.py
uPyExplorer/Terminal.py
uPyExplorer/Tree.py
uPyExplorer/UnixPyTree.py
uPyExplorer/__init__.py
uPyExplorer/__main__.py
uPyExplorer/buttonToolTyp.py
uPyExplorer/uPyExp.py
uPyExplorer/uPyExplorer.ico
uPyExplorer/uPyExplorer.png
uPyExplorer/uPyExplorer.xbm
uPyExplorer-1.16.0.dist-info/METADATA
uPyExplorer-1.16.0.dist-info/WHEEL
uPyExplorer-1.16.0.dist-info/entry_points.txt
uPyExplorer-1.16.0.dist-info/top_level.txt
uPyExplorer-1.16.0.dist-info/RECORD
