Metadata-Version: 2.1
Name: uPyExplorer
Version: 1.16.0
Summary: Explorer for Micropython Device
Home-page: https://github.com/RetepRelleum/uPyExplorer
Author: Real Python
Author-email: retep.relleum@bluewin.ch
License: MIT
Platform: UNKNOWN
Classifier: License :: OSI Approved :: MIT License
Classifier: Programming Language :: Python :: 3
Classifier: Programming Language :: Python :: 3.7
Requires-Dist: pyserial
